{
  "id": "aws-waf",
  "name": "AWS WAF",
  "category": "Anti-Bot",
  "confidence": 100,
  "lastUpdated": "2024-01-15",
  "version": "1.0.0",
  "website": "https://aws.amazon.com/waf/",
  "icon": "aws.png",
  "description": "Amazon Web Services Web Application Firewall with bot control",
  "tags": ["waf", "bot-protection", "aws", "cloud-security", "ddos-protection"],
  "detection": {
    "cookies": [
      {
        "name": "aws-waf-token",
        "confidence": 95,
        "description": "AWS WAF session token"
      },
      {
        "name": "awswaf*",
        "confidence": 90,
        "description": "AWS WAF cookies"
      }
    ],
    "headers": [
      {
        "name": "X-Amzn-RequestId",
        "confidence": 85,
        "description": "AWS request identifier"
      },
      {
        "name": "X-Amzn-ErrorType",
        "confidence": 90,
        "description": "AWS error type header"
      },
      {
        "name": "X-Amzn-Trace-Id",
        "confidence": 80,
        "description": "AWS trace identifier"
      },
      {
        "name": "X-Amzn-WAF-*",
        "confidence": 95,
        "description": "AWS WAF specific headers"
      }
    ],
    "urls": [
      {
        "pattern": "/challenge.js",
        "confidence": 80,
        "description": "AWS WAF challenge script"
      },
      {
        "pattern": "awswaf",
        "confidence": 85,
        "description": "AWS WAF in URL"
      }
    ],
    "scripts": [
      {
        "content": "challenge.js",
        "confidence": 80,
        "description": "AWS WAF challenge script"
      },
      {
        "content": "awswaf",
        "confidence": 85,
        "description": "AWS WAF reference"
      }
    ],
    "dom": [
      {
        "selector": "meta[name*='aws']",
        "confidence": 75,
        "description": "AWS meta tags"
      }
    ]
  },
  "mitigation": {
    "difficulty": "High",
    "techniques": [
      "Rate limiting",
      "Geo-blocking",
      "IP reputation lists",
      "Regex pattern matching",
      "Bot Control rule group",
      "JavaScript challenge"
    ],
    "bypass_methods": [
      "Residential proxies",
      "Solving JavaScript challenges",
      "Request throttling",
      "User-Agent rotation"
    ]
  }
}